setup.py
simpledb.py
simpledb.egg-info/PKG-INFO
simpledb.egg-info/SOURCES.txt
simpledb.egg-info/dependency_links.txt
simpledb.egg-info/top_level.txt